supert5/__init__.py
supert5/heads/__init__.py
supert5/heads/decoder_heds.py
supert5/heads/encoder_heads.py
supert5/heads/t5_heads.py
supert5/model/__init__.py
supert5/model/attentions.py
supert5/model/config.py
supert5/model/modeling.py
supert5/model/modules.py
supert5/model/utils.py
supert5/ops/__init__.py
supert5/ops/attention_bias.py
supert5/ops/flash_attention.py
supert5/ops/fused_bias_attention.py
supert5/ops/gated_mlp.py
supert5/ops/naive_attention.py
supert5/ops/rms_norm.py
supert5-0.0.3.dist-info/METADATA
supert5-0.0.3.dist-info/WHEEL
supert5-0.0.3.dist-info/RECORD
