Metadata-Version: 2.1
Name: superT5
Version: 0.0.3
Summary: Memory and compute efficient T5 models.
License: Apache-2.0
Author: knowledgator.com
Requires-Python: >=3.10,<4.0
Classifier: License :: OSI Approved :: Apache Software License
Classifier: Programming Language :: Python :: 3
Classifier: Programming Language :: Python :: 3.10
Classifier: Programming Language :: Python :: 3.11
Classifier: Programming Language :: Python :: 3.12
Requires-Dist: torch (>=2.1.0)
Requires-Dist: transformers (>=4.30.0)
Requires-Dist: triton (>=2.2.0)
